stripper.py
csv_stripper-1.0.dist-info/METADATA
csv_stripper-1.0.dist-info/WHEEL
csv_stripper-1.0.dist-info/entry_points.txt
csv_stripper-1.0.dist-info/top_level.txt
csv_stripper-1.0.dist-info/RECORD
