Metadata-Version: 2.1
Name: csv-stripper
Version: 1.0
Summary: UNKNOWN
Home-page: https://github.com/alvarezGarciaMarcos/csv-stripper
Author: UNKNOWN
Author-email: UNKNOWN
License: UNKNOWN
Download-URL: https://github.com/alvarezGarciaMarcos/csv-stripper/archive/1.0.tar.gz
Platform: UNKNOWN
Requires-Dist: click
